[
    {
        "id": "877d76f9-3c31-4831-8758-eccf4e51d96a",
        "agent": "Viper",
        "map": "Pearl",
        "side": "Attacking",
        "title": "Poison Cloud Lurk for Mail From A Main",
        "description": "Throw this orb lineup to pressure Defenders at Art, as it threatens and isolates the A Site player from the Art player.",
        "ability": "Q",
        "type": "LU",
        "src": "https://blitz-cdn-videos.blitz.gg/valorant/guides/viper-pearl-atk-mail-amain-orb_2.mp4#t=0.1"
    },
    {
        "id": "d8e52fd0-f221-4146-952d-30595219749c",
        "agent": "Viper",
        "map": "Pearl",
        "side": "Attacking",
        "title": "Default Attacker Wall for B Site From Shop",
        "description": "Throw this wall as soon as preparation phase ends for a strong default wall. This wall prevents Defenders from successfully spotting your lurk to link, and can be used to execute B Site late into the round.",
        "ability": "E",
        "type": "LU",
        "src": "https://blitz-cdn-videos.blitz.gg/valorant/guides/viper-pearl-atk-bsite-market-wall_1.mp4#t=0.1"
    },
    {
        "id": "f4f8ce7b-aeac-46b9-bd47-4e45f10386a7",
        "agent": "Viper",
        "map": "Pearl",
        "side": "Attacking",
        "title": "A Site Execute Wall for Art + Orb for Dug Out",
        "description": "Enable your team to successfully take A Site with this combination of Viper utility, you can choose to position your wall closer or further away to the site.",
        "ability": "E",
        "type": "LU",
        "src": "https://blitz-cdn-videos.blitz.gg/valorant/guides/viper-pearl-atk-asite-amain-wall_2.mp4#t=0.1"
    },
    {
        "id": "08f78aed-4eb6-4115-9cce-cfed3f768aec",
        "agent": "Viper",
        "map": "Pearl",
        "side": "Attacking",
        "title": "B Heaven Poison Cloud Execute From Shops",
        "description": "Here's a powerful lineup you can use to enhance your B Site execute, Defenders cannot peek through the orb.",
        "ability": "Q",
        "type": "LU",
        "src": "https://blitz-cdn-videos.blitz.gg/valorant/guides/viper-pearl-atk-bheaven-market-orb_2.mp4#t=0.1"
    },
    {
        "id": "f344f565-d3b8-4237-b342-6e16e7e7e300",
        "agent": "Viper",
        "map": "Pearl",
        "side": "Attacking",
        "title": "B Site Default Post Plant Snakebite from B Ramp",
        "description": "Here's a great post plant Snakebite lineup from B Ramp.",
        "ability": "C",
        "type": "LU",
        "src": "https://blitz-cdn-videos.blitz.gg/valorant/guides/pearl-viper-atk-bsite-blink-snakebite.mp4#t=0.1"
    },
    {
        "id": "9be3aec6-8a89-458c-8b50-5c320cc5b7dd",
        "agent": "Viper",
        "map": "Pearl",
        "side": "Attacking",
        "title": "A Site Default Post Plant Snakebite from A Main",
        "description": "Here's a great post plant Snakebite lineup from A Main.",
        "ability": "C",
        "type": "LU",
        "src": "https://blitz-cdn-videos.blitz.gg/valorant/guides/pearl-viper-atk-asite-backamain-snakebite.mp4#t=0.1"
    },
    {
        "id": "979c34a7-2fee-491f-824b-eb6514b9861a",
        "agent": "Viper",
        "map": "Pearl",
        "side": "Defending",
        "title": "Start Round Art + Double Doors Pit",
        "description": "Use this extremely powerful Viper ultimate to effectively lockdown mid control. This ultimate allows your art player to play inside of it, or outside and have it act as a smoke.",
        "ability": "X",
        "type": "LU",
        "src": "https://blitz-cdn-videos.blitz.gg/valorant/guides/viper-pearl-def-ddoors-link-pit_1.mp4#t=0.1"
    },
    {
        "id": "9b82d3ce-6905-4776-b4d1-ffe07c34a806",
        "agent": "Viper",
        "map": "Pearl",
        "side": "Defending",
        "title": "Double Doors One Way Poison Cloud From Link",
        "description": "Throw your orb, as shown in the video, when preparation phase ends for a strong one way orb at doors.",
        "ability": "Q",
        "type": "LU",
        "src": "https://blitz-cdn-videos.blitz.gg/valorant/guides/viper-pearl-def-ddors-link-orb_2.mp4#t=0.1"
    },
    {
        "id": "0649cdc2-9eb6-450e-9fa5-db160d30a582",
        "agent": "Viper",
        "map": "Pearl",
        "side": "Defending",
        "title": "Standard B Site Defender Wall to Screens",
        "description": "Here's an easy, yet effective wall you can throw at the start of the round. Use this to retake, or contest the B Site. There's a little pocket for you to hide in screens to potentially make a round winning play.",
        "ability": "E",
        "type": "LU",
        "src": "https://blitz-cdn-videos.blitz.gg/valorant/guides/viper-pearl-def-blong-link-wall_1.mp4#t=0.1"
    },
    {
        "id": "1e659161-6ba5-44d3-bfb2-f9e672e184ad",
        "agent": "Viper",
        "map": "Pearl",
        "side": "Defending",
        "title": "One Way Orb for Art Entrance From Art",
        "description": "As soon as preparation phase ends, line yourself up like so and throw your orb for a strong one way.",
        "ability": "Q",
        "type": "LU",
        "src": "https://blitz-cdn-videos.blitz.gg/valorant/guides/viper-pearl-def-art-art-orb_2.mp4#t=0.1"
    },
    {
        "id": "a95fda1f-ac01-4a88-bf93-5a077ff75093",
        "agent": "Viper",
        "map": "Pearl",
        "side": "Defending",
        "title": "Full Utility Setup for B Site and B Link",
        "description": "Here's a very effective full utility setup for B Site and B Link",
        "ability": "E",
        "type": "LU",
        "src": "https://blitz-cdn-videos.blitz.gg/valorant/guides/pearl-viper-def-bsite-blink-toxicscreen.mp4#t=0.1"
    },
    {
        "id": "73d77a3f-3ec2-4e04-853e-a68034ab97e9",
        "agent": "Viper",
        "map": "Lotus",
        "side": "Attacking",
        "title": "Simple B Site Post Plant lineup from A Link / A Main",
        "description": "Use this simple Snake Bite post plant lineup from A Link / A Main to delay enemy Defenders from defusing the Spike from a position that may be tricky for them to push into to stop you.",
        "ability": "C",
        "type": "LU",
        "src": "https://blitz-cdn-videos.blitz.gg/valorant/guides/viper-lotus-atk-bsite-alink-snakebite.mp4#t=0.1"
    },
    {
        "id": "24d5ec55-5b5d-4c9f-91f0-68d7467ab379",
        "agent": "Viper",
        "map": "Lotus",
        "side": "Attacking",
        "title": "C Lobby to C Site Default Snake Bite Lineup",
        "description": "Here's a Snake Bite that you can throw from C Lobby to delay or deny the spike defuse on C Site Default.",
        "ability": "C",
        "type": "LU",
        "src": "https://blitz-cdn-videos.blitz.gg/valorant/guides/viper-lotus-atk-csite-clobby-snakebite.mp4#t=0.1"
    },
    {
        "id": "e90feb9b-8901-4cd0-8e95-13fae384401c",
        "agent": "Viper",
        "map": "Lotus",
        "side": "Attacking",
        "title": "B Pillars to B Site Post Plant Snake Bite",
        "description": "Here's a simple, but effective B Site Post Plant Snake Bite from B Pillars.",
        "ability": "C",
        "type": "LU",
        "src": "https://blitz-cdn-videos.blitz.gg/valorant/guides/viper-lotus-atk-bsite-bpillar-snakebite.mp4#t=0.1"
    },
    {
        "id": "298a2e84-b0bb-4296-8a20-1c80f0913a85",
        "agent": "Viper",
        "map": "Lotus",
        "side": "Attacking",
        "title": "Simple A Site Post Plant Snake Bite",
        "description": "Here's a simple, but effective post plant Snake Bite lineup for A Site.",
        "ability": "C",
        "type": "LU",
        "src": "https://blitz-cdn-videos.blitz.gg/valorant/guides/viper-lotus-atk-asite-alink-snakebite.mp4#t=0.1"
    },
    {
        "id": "d2c5abdf-6544-4ba4-b879-f47187c78516",
        "agent": "Viper",
        "map": "Lotus",
        "side": "Defending",
        "title": "C Site Delay Snake Bites to Allow Rotate",
        "description": "Use this delay Snake Bites to delay enemy players from freely pushing into the areas on Site that they want to push into to give your team time to rotate and retake Site with you.",
        "ability": "C",
        "type": "LU",
        "src": "https://blitz-cdn-videos.blitz.gg/valorant/guides/viper-lotus-def-csite-clink-snakebite.mp4#t=0.1"
    },
    {
        "id": "fe4a7c2f-d435-4889-b8fe-79dbfbe64d44",
        "agent": "Viper",
        "map": "Lotus",
        "side": "Defending",
        "title": "A, B, and C Toxic Screen + Poison Orb Chokepoint Control",
        "description": "Use this setup to control several key chokepoints throughout the map on all three Sites.",
        "ability": "E",
        "type": "LU",
        "src": "https://blitz-cdn-videos.blitz.gg/valorant/guides/viper-lotus-def-bsite-csite-toxicscreen.mp4#t=0.1"
    },
    {
        "id": "61051847-ff02-4f79-a966-055af7be06b4",
        "agent": "Omen",
        "map": "Haven",
        "side": "Attacking",
        "title": "Standard B Site Execute Dark Cover Placements",
        "description": "Here are the default Dark Cover placements for an B Site Execute.",
        "ability": "E",
        "type": "LU",
        "src": "https://blitz-cdn-videos.blitz.gg/valorant/guides/haven-omen-atk-bsite-mid-darkcover.mp4#t=0.1"
    },
    {
        "id": "11c493e6-7b4a-4d2e-87cd-2cab3b4f5827",
        "agent": "Omen",
        "map": "Haven",
        "side": "Attacking",
        "title": "Standard C Site Execute Dark Cover Placements",
        "description": "Here are the default Dark Cover placements for an C Site Execute.",
        "ability": "E",
        "type": "LU",
        "src": "https://blitz-cdn-videos.blitz.gg/valorant/guides/omen-haven-atk-csite-clong-darkcover.mp4#t=0.1"
    },
    {
        "id": "4d988223-b9db-4c40-8d65-47208e783404",
        "agent": "Omen",
        "map": "Haven",
        "side": "Defending",
        "title": "A Site Retake Dark Covers + Paranoia",
        "description": "Use these Dark Covers + Paranoia to either make it more difficult for the Attackers to push into A Site, or to retake Site. Callout that you are using / you want to use your Paranoia before using it so that your teammates can work off of the Paranoia and take advantage of the opportunities the Paranoia can create for your team.",
        "ability": "E",
        "type": "LU",
        "src": "https://blitz-cdn-videos.blitz.gg/valorant/guides/omen-haven-def-asite-alink-darkcover_1.mp4#t=0.1"
    },
    {
        "id": "3bde65b7-24e7-46df-b090-39b0234bd887",
        "agent": "Omen",
        "map": "Haven",
        "side": "Defending",
        "title": "Paranoia to Hold B, C, and Garage from Window",
        "description": "Use these Paranoia Variations to make it more difficult for enemy players to push through B, C, or C Garage.",
        "ability": "E",
        "type": "LU",
        "src": "https://blitz-cdn-videos.blitz.gg/valorant/guides/omen-haven-def-cgarage-cwindow-darkcover.mp4#t=0.1"
    },
    {
        "id": "b7a55dd6-cc03-4d2b-abe4-0b2097a7310b",
        "agent": "Omen",
        "map": "Haven",
        "side": "Defending",
        "title": "C Site Retake / Site Hold Dark Covers",
        "description": "Use these C Site retake / Site Hold Dark Covers to make it more difficult for enemy players to push into and then hold Site at different stages of retaking / holding Site.",
        "ability": "E",
        "type": "LU",
        "src": "https://blitz-cdn-videos.blitz.gg/valorant/guides/omen-haven-def-csite-clink-darkcover.mp4#t=0.1"
    },
    {
        "id": "6bb02f0b-d6ea-4154-9e60-4335f5676430",
        "agent": "Omen",
        "map": "Split",
        "side": "Defending",
        "title": "How to Play from A Tower",
        "description": "When playing from A Tower, use these smoke to make it more difficult for enemy players to push through key chokepoints that would allow them to take control of A Site.",
        "ability": "E",
        "type": "LU",
        "src": "https://blitz-cdn-videos.blitz.gg/valorant/guides/omen-split-def-asite-atower-darkcover_1.mp4#t=0.1"
    },
    {
        "id": "336d58d4-3644-42f5-8187-5bd9af319bfb",
        "agent": "Omen",
        "map": "Split",
        "side": "Defending",
        "title": "How to play from B Tower",
        "description": "Use this simple, but effective Dark Cover + Paranoia combo to hold down B Site and make it more difficult for enemy players to push into Site.",
        "ability": "Q",
        "type": "LU",
        "src": "https://blitz-cdn-videos.blitz.gg/valorant/guides/omen-split-def-mid-btower-darkcover.mp4#t=0.1"
    },
    {
        "id": "7ee1eb52-cb48-4516-8a79-1a553c3c6fe8",
        "agent": "Omen",
        "map": "Ascent",
        "side": "Attacking",
        "title": "Aggressive Bottom Mid Dark Covers",
        "description": "Use these aggressive bottom Mid Dark Covers to contest Mid with your team, and / or set your team up to push through market into B Site after taking control of Mid.",
        "ability": "E",
        "type": "LU",
        "src": "https://blitz-cdn-videos.blitz.gg/valorant/guides/omen-ascent-atk-mid-midtiles-darkcover.mp4#t=0.1"
    },
    {
        "id": "b776bee3-c49c-489b-9ad1-b10b6106c576",
        "agent": "Omen",
        "map": "Ascent",
        "side": "Attacking",
        "title": "Standard A Site Dark Cover Placement + Simple Paranoia",
        "description": "Use these standard smokes when executing onto A Site, and combo it with your paranoia just before your team pushes out of A Main to create opportunities for them.",
        "ability": "E",
        "type": "LU",
        "src": "https://blitz-cdn-videos.blitz.gg/valorant/guides/omen-ascent-atk-asite-amain-darkcover_1.mp4#t=0.1"
    },
    {
        "id": "13766e0d-512b-4b2a-8500-79c5b9dc10b4",
        "agent": "Omen",
        "map": "Ascent",
        "side": "Attacking",
        "title": "Standard B Site Dark Cover Placement + Simple Paranoia",
        "description": "Use these standard smokes when executing onto B Site, and combo it with your Paranoia just before your team pushes out of B Main to create opportunities for them.",
        "ability": "E",
        "type": "LU",
        "src": "https://blitz-cdn-videos.blitz.gg/valorant/guides/omen-ascent-atk-bsite-bmain-darkcover_1.mp4#t=0.1"
    },
    {
        "id": "d17e21a5-c792-47fb-91f3-68332f619182",
        "agent": "Omen",
        "map": "Ascent",
        "side": "Attacking",
        "title": "A Site Default Smokes",
        "description": "These are two good smokes to help your team get into A Site while blocking off the other entry points into the site.",
        "ability": "E",
        "type": "LU",
        "src": "https://blitz-cdn-videos.blitz.gg/valorant/guides/3omen-ascent.mp4#t=0.1"
    },
    {
        "id": "978bf2f0-e06d-4215-8ace-8de3067fd2ac",
        "agent": "Omen",
        "map": "Ascent",
        "side": "Defending",
        "title": "Mid Support / Control Dark Covers",
        "description": "Use these Dark Covers to support your team in Mid, and make it more difficult for the enemy team to contest Mid.",
        "ability": "E",
        "type": "LU",
        "src": "https://blitz-cdn-videos.blitz.gg/valorant/guides/omen-ascent-def-mid-atree-darkcover.mp4#t=0.1"
    },
    {
        "id": "feeb1910-10ac-497f-bdac-a722a71e9b9c",
        "agent": "Omen",
        "map": "Ascent",
        "side": "Defending",
        "title": "A Site Hold Dark Cover + Paranoia",
        "description": "Use this Dark Cover to delay enemy players from pushing into A Site when the enemy team is showing indicators that they are about to push into Site to give your teammates time to rotate toward the side of A.",
        "ability": "E",
        "type": "LU",
        "src": "https://blitz-cdn-videos.blitz.gg/valorant/guides/omen-ascent-def-asite-atree-darkcoer.mp4#t=0.1"
    },
    {
        "id": "572934eb-22d5-4079-b1b2-c53181bc336b",
        "agent": "Omen",
        "map": "Ascent",
        "side": "Defending",
        "title": "B Main Dark Cover + Simple Paranoia to Hold B",
        "description": "Use this simple B Main Dark Cover and Simple Paranoia when the Attackers are executing into B Site through B Main to break up their push.",
        "ability": "E",
        "type": "LU",
        "src": "https://blitz-cdn-videos.blitz.gg/valorant/guides/omen-ascent-def-blane-market-darkcover.mp4#t=0.1"
    },
    {
        "id": "ebae37d7-aaca-4362-86f2-c81c00eed3e2",
        "agent": "Omen",
        "map": "Ascent",
        "side": "Defending",
        "title": "Early Round A Main One Way",
        "description": "Here's a simple, but effective early round A Main one way smoke that is typically used to support your teammate's efforts to control A Main.",
        "ability": "E",
        "type": "LU",
        "src": "https://blitz-cdn-videos.blitz.gg/valorant/guides/omen-ascent-def-amain-asite-darkcover.mp4#t=0.1"
    },
    {
        "id": "3fdafeb0-8a84-4ff3-9669-b95c6fa0a0a7",
        "agent": "Omen",
        "map": "Icebox",
        "side": "Attacking",
        "title": "B Tube to Mid Boiler Dark Cover",
        "description": "This is a good smoke to block mid boiler and allow your team to cross without being killed by an oper. This smoke is also nice because it allows you to see your opponent if they push forward and drop.",
        "ability": "E",
        "type": "LU",
        "src": "https://blitz-cdn-videos.blitz.gg/valorant/guides/omen-icebox-atk-btube-midboiler-darkcover.mp4#t=0.1"
    },
    {
        "id": "4f50443b-63c2-48c2-8ce2-69a352da858c",
        "agent": "Omen",
        "map": "Icebox",
        "side": "Attacking",
        "title": "A Pipes to A Site Box Paranoia",
        "description": "This is a good paranoia to blind the entire right side of A Site during an A execute.",
        "ability": "Q",
        "type": "LU",
        "src": "https://blitz-cdn-videos.blitz.gg/valorant/guides/omen-icebox-atk-apipes-asitebox-paranoia.mp4#t=0.1"
    },
    {
        "id": "17c3c6b3-c268-416e-91e9-90b0dbd81aec",
        "agent": "Omen",
        "map": "Icebox",
        "side": "Attacking",
        "title": "A Pipes to A Heaven Dark Cover",
        "description": "This is a good one way smoke to block the back side of site and allow your team to get into site during an execute.",
        "ability": "E",
        "type": "LU",
        "src": "https://blitz-cdn-videos.blitz.gg/valorant/guides/omen-icebox-atk-apipes-aheaven-darkcover.mp4#t=0.1"
    },
    {
        "id": "ab6bbb04-4bdb-4fa8-9530-cca58e67b2bc",
        "agent": "Omen",
        "map": "Icebox",
        "side": "Attacking",
        "title": "Mid Blue to B Orange Dark Cover",
        "description": "This is a good dark cover to allow safe passage to B Orange and not let the opponent see you cross.",
        "ability": "E",
        "type": "LU",
        "src": "https://blitz-cdn-videos.blitz.gg/valorant/guides/omen-icebox-atk-midblue-borange-darkcover.mp4#t=0.1"
    }
]